LICENSE
MANIFEST.in
README.md
requirements.txt
setup.py
指令.md
jhpycode/__init__.py
jhpycode/card_wash.py
jhpycode/data_fenxi.py
jhpycode/data_get.py
jhpycode/data_layer.py
jhpycode/data_pivot.py
jhpycode/data_to_all.py
jhpycode/file_tool.py
jhpycode/mydf.py
jhpycode/wash_tool.py
jhpycode.egg-info/PKG-INFO
jhpycode.egg-info/SOURCES.txt
jhpycode.egg-info/dependency_links.txt
jhpycode.egg-info/top_level.txt