Metadata-Version: 2.1
Name: jhpycode
Version: 1.0.5
Summary: 自用分析银行卡
Home-page: 
Author: PJH
Author-email: ppsq7777@163.com
Classifier: Programming Language :: Python :: 3
Classifier: License :: OSI Approved :: MIT License
Classifier: Operating System :: OS Independent
Requires-Python: >=3.6
License-File: LICENSE
